{
  "name": "03 Estimation Planning",
  "path": "/blogs/system-design/01-fundamentals/03-estimation-planning",
  "blogs": [
    {
      "title": "Back-of-the-Envelope Calculations",
      "description": "A practical guide to back-of-the-envelope estimation for system design — traffic, storage, bandwidth, server capacity, and power-of-2 reference values",
      "date": "2026-05-14",
      "author": "Abhishek Tiwari",
      "tags": [
        "estimation",
        "capacity-planning",
        "system-design",
        "scalability",
        "performance"
      ],
      "coverImage": "",
      "draft": false,
      "category": "system-design",
      "hierarchy": [
        "01-fundamentals",
        "03-estimation-planning"
      ],
      "slug": "64. back-of-envelope-calculations",
      "path": "/blogs/system-design/01-fundamentals/03-estimation-planning/64. back-of-envelope-calculations"
    }
  ]
}