{
  "name": "Runtime",
  "path": "/blogs/backend/programming/golang/runtime",
  "blogs": [
    {
      "title": "Go Runtime: Scheduler, GC, and Internals",
      "description": "Deep dive into Go runtime: GMP scheduler, garbage collector, memory allocator, network poller, and runtime internals",
      "date": "2026-05-14",
      "author": "Abhishek Tiwari",
      "tags": [
        "go",
        "runtime",
        "scheduler",
        "gc",
        "internals"
      ],
      "coverImage": "/images/go-runtime.png",
      "draft": false,
      "category": "backend",
      "hierarchy": [
        "programming",
        "golang",
        "runtime"
      ],
      "slug": "go-runtime-internals",
      "path": "/blogs/backend/programming/golang/runtime/go-runtime-internals"
    }
  ]
}